{
  "id": "antler-flowlly",
  "name": "Flowlly",
  "slug": "flowlly",
  "website": "https://www.flowlly.com/",
  "description": "AI Construction Workers",
  "founded_year": 2022,
  "location": "Canada",
  "sector": "Industrials",
  "logo_url": "https://cdn.prod.website-files.com/62d6de70dd9e54fe5d03255a/67dde27175b0e307cb57de4c_portfolio%252Fcompany%252Fc292cf95-2960-4124-ab84-49fff6fd40a4%252F1733119230505-logo.avif",
  "url": "https://www.antler.co/portfolio/flowlly",
  "api": "https://antler-api.github.io/companies/flowlly.json"
}