{
  "id": "antler-onecliq-io",
  "name": "Onecliq.io",
  "slug": "onecliq-io",
  "website": "https://minuteskill.com/",
  "description": "MinuteSkill is a social micro-learning platform to entrepreneurs, innovators",
  "founded_year": 2022,
  "location": "Canada",
  "sector": "ConsumerTech",
  "logo_url": "https://cdn.prod.website-files.com/62d6de70dd9e54fe5d03255a/67dde32bd7b266f64d4c3f04_portfolio%252Fcompany%252F5fe96edf-89bf-4535-9077-976a048a04ea%252F1733119268045-logo.avif",
  "url": "https://www.antler.co/portfolio/onecliq-io",
  "api": "https://antler-api.github.io/companies/onecliq-io.json"
}