{
  "id": "antler-sahaj-gaming",
  "name": "Sahaj Gaming",
  "slug": "sahaj-gaming",
  "website": "https://sahajgaming.com/",
  "description": "Building casual, select real money games starting with Ludo.",
  "founded_year": 2023,
  "location": "India",
  "sector": "ConsumerTech",
  "logo_url": "https://cdn.prod.website-files.com/62d6de70dd9e54fe5d03255a/67f3c42ba4aceef3deabde7d_portfolio%252Fcompany%252F59987848-51c7-40ff-aa5f-d815bc82e520%252F1744028693734-Sahaj%2520Gaming.avif",
  "url": "https://www.antler.co/portfolio/sahaj-gaming",
  "api": "https://antler-api.github.io/companies/sahaj-gaming.json"
}