{
  "id": "antler-struct-finance",
  "name": "Struct Finance",
  "slug": "struct-finance",
  "website": "https://struct.fi/",
  "description": "Structured financial instruments across chains that maximize returns and reduce risk for investors.",
  "founded_year": 2021,
  "location": "Unknown",
  "sector": "Unknown",
  "logo_url": "https://cdn.prod.website-files.com/62d6de70dd9e54fe5d03255a/66b45390819993b26dab8bc3_HR4N6gbGSLNk3DfA6fLzK-mEXgfKdbhtReRBZ6AoviI.avif",
  "url": "https://www.antler.co/portfolio/struct-finance",
  "api": "https://antler-api.github.io/companies/struct-finance.json"
}