{
  "id": "antler-superflex",
  "name": "Superflex ⚡️",
  "slug": "superflex",
  "website": "https://www.superflex.ai/",
  "description": "Figma -> Production-ready code in seconds.",
  "founded_year": 2024,
  "location": "Unknown",
  "sector": "B2B Software",
  "logo_url": "https://cdn.prod.website-files.com/62d6de70dd9e54fe5d03255a/679e468f1e7c1370d67dcaf4_teams%252F4f113dd8-0f13-48a1-ae99-fd17778f191a%252Flogos%252FSuperflex-05.avif",
  "url": "https://www.antler.co/portfolio/superflex",
  "api": "https://antler-api.github.io/companies/superflex.json"
}