{
  "id": "antler-youth-health-tech",
  "name": "Youth Health Tech",
  "slug": "youth-health-tech",
  "website": "https://www.youth-healthtech.com",
  "description": "Full health checkups in less than 2 minutes.",
  "founded_year": 2023,
  "location": "Germany",
  "sector": "Health and BioTech",
  "logo_url": "https://cdn.prod.website-files.com/62d6de70dd9e54fe5d03255a/6842972fad2bf84dfd216c8b_portfolio%252Fcompany%252F62b2fbfe-714c-4029-951c-2f06e6f85cda%252F1726738058952-Youth_new_logo.avif",
  "url": "https://www.antler.co/portfolio/youth-health-tech",
  "api": "https://antler-api.github.io/companies/youth-health-tech.json"
}